tom_tns/__init__.py
tom_tns/admin.py
tom_tns/apps.py
tom_tns/forms.py
tom_tns/hermes_api.py
tom_tns/migrations/__init__.py
tom_tns/models.py
tom_tns/templates/tom_tns/partials/tns_button.html
tom_tns/templates/tom_tns/partials/tns_classify_form.html
tom_tns/templates/tom_tns/partials/tns_report_form.html
tom_tns/templates/tom_tns/tns_report.html
tom_tns/templatetags/__init__.py
tom_tns/templatetags/tns_extras.py
tom_tns/tests/__init__.py
tom_tns/tests/boot_django.py
tom_tns/tests/django_shell.py
tom_tns/tests/run_tests.py
tom_tns/tests/tests.py
tom_tns/tns_api.py
tom_tns/urls.py
tom_tns/views.py
tom_tns-0.3.5.dist-info/METADATA
tom_tns-0.3.5.dist-info/WHEEL
tom_tns-0.3.5.dist-info/licenses/LICENSE
tom_tns-0.3.5.dist-info/RECORD
