Metadata-Version: 2.4
Name: tom-tns
Version: 0.3.5
Summary: TOMtoolkit module for reporting transients to the TNS
License-Expression: GPL-3.0-or-later
License-File: LICENSE
Author: Joseph Chatelain
Author-email: jchatelain@lco.global
Requires-Python: >=3.9,<3.13
Classifier: Programming Language :: Python :: 3
Classifier: Programming Language :: Python :: 3.9
Classifier: Programming Language :: Python :: 3.10
Classifier: Programming Language :: Python :: 3.11
Classifier: Programming Language :: Python :: 3.12
Requires-Dist: tomtoolkit (>=2.28.0,<3)
